[
    {
        "user_info": {
            "email": "Unknownboy8680@gmail.com",
            "year": "2K22",
            "department": "BCA"
        },
        "access_permissions": {
            "fundamentals": {
                "enabled": true,
                "modules": {
                    "basic_io": true,
                    "conditional_statements": true,
                    "looping": true,
                    "patterns": true,
                    "number_operations": true,
                    "number_problems": true,
                    "arrays": true,
                    "strings": true,
                    "functions_pointers": true,
                    "structures": true
                }
            },
            "assessments": {
                "enabled": false,
                "modules": {
                    "phase_1": false,
                    "phase_2": false,
                    "phase_3": false,
                    "final": false
                }
            },
            "company_specific": {
                "enabled": false,
                "modules": {
                    "accenture": false,
                    "cts": false,
                    "capgemini": false,
                    "infosys": false,
                    "tcs": false,
                    "wipro": false,
                    "zoho": false
                }
            },
            "special_tracks": {
                "enabled": false,
                "modules": {
                    "real_time_problems": false
                }
            },
            "dsa": {
                "enabled": false,
                "modules": {}
            },
            "advanced_topics": {
                "enabled": false,
                "modules": {}
            },
            "projects": {
                "enabled": false,
                "modules": {}
            },
            "interview_prep": {
                "enabled": false,
                "modules": {}
            }
        }
    },
    {
        "user_info": {
            "email": "dharsan1115@gmail.com",
            "year": "2K22",
            "department": "BCA"
        },
        "access_permissions": {
            "fundamentals": {
                "enabled": true,
                "modules": {
                    "basic_io": true,
                    "conditional_statements": true,
                    "looping": true,
                    "patterns": true,
                    "number_operations": true,
                    "number_problems": true,
                    "arrays": true,
                    "strings": true,
                    "functions_pointers": true,
                    "structures": true
                }
            },
            "assessments": {
                "enabled": false,
                "modules": {
                    "phase_1": false,
                    "phase_2": false,
                    "phase_3": false,
                    "final": false
                }
            },
            "company_specific": {
                "enabled": false,
                "modules": {
                    "accenture": false,
                    "cts": false,
                    "capgemini": false,
                    "infosys": false,
                    "tcs": false,
                    "wipro": false,
                    "zoho": false
                }
            },
            "special_tracks": {
                "enabled": false,
                "modules": {
                    "real_time_problems": false
                }
            },
            "dsa": {
                "enabled": false,
                "modules": {}
            },
            "advanced_topics": {
                "enabled": false,
                "modules": {}
            },
            "projects": {
                "enabled": false,
                "modules": {}
            },
            "interview_prep": {
                "enabled": false,
                "modules": {}
            }
        }
    },
    {
        "user_info": {
            "email": "satachsaram@gmail.com",
            "year": "2K22",
            "department": "BCA"
        },
        "access_permissions": {
            "fundamentals": {
                "enabled": true,
                "modules": {
                    "basic_io": true,
                    "conditional_statements": true,
                    "looping": true,
                    "patterns": true,
                    "number_operations": true,
                    "number_problems": true,
                    "arrays": true,
                    "strings": true,
                    "functions_pointers": true,
                    "structures": true
                }
            },
            "assessments": {
                "enabled": false,
                "modules": {
                    "phase_1": false,
                    "phase_2": false,
                    "phase_3": false,
                    "final": false
                }
            },
            "company_specific": {
                "enabled": false,
                "modules": {
                    "accenture": false,
                    "cts": false,
                    "capgemini": false,
                    "infosys": false,
                    "tcs": false,
                    "wipro": false,
                    "zoho": false
                }
            },
            "special_tracks": {
                "enabled": false,
                "modules": {
                    "real_time_problems": false
                }
            },
            "dsa": {
                "enabled": false,
                "modules": {}
            },
            "advanced_topics": {
                "enabled": false,
                "modules": {}
            },
            "projects": {
                "enabled": false,
                "modules": {}
            },
            "interview_prep": {
                "enabled": false,
                "modules": {}
            }
        }
    },
    {
        "user_info": {
            "email": "vellivelli08@gmail.com",
            "year": "2K22",
            "department": "BCOM_CA"
        },
        "access_permissions": {
            "fundamentals": {
                "enabled": true,
                "modules": {
                    "basic_io": true,
                    "conditional_statements": true,
                    "looping": true,
                    "patterns": true,
                    "number_operations": true,
                    "number_problems": true,
                    "arrays": true,
                    "strings": true,
                    "functions_pointers": true,
                    "structures": true
                }
            },
            "assessments": {
                "enabled": false,
                "modules": {
                    "phase_1": false,
                    "phase_2": false,
                    "phase_3": false,
                    "final": false
                }
            },
            "company_specific": {
                "enabled": false,
                "modules": {
                    "accenture": false,
                    "cts": false,
                    "capgemini": false,
                    "infosys": false,
                    "tcs": false,
                    "wipro": false,
                    "zoho": false
                }
            },
            "special_tracks": {
                "enabled": false,
                "modules": {
                    "real_time_problems": false
                }
            },
            "dsa": {
                "enabled": false,
                "modules": {}
            },
            "advanced_topics": {
                "enabled": false,
                "modules": {}
            },
            "projects": {
                "enabled": false,
                "modules": {}
            },
            "interview_prep": {
                "enabled": false,
                "modules": {}
            }
        }
    },
    {
        "user_info": {
            "email": "annaduraianandhi96@gmail.com",
            "year": "2K24",
            "department": "BCOM_CA"
        },
        "access_permissions": {
            "fundamentals": {
                "enabled": true,
                "modules": {
                    "basic_io": true,
                    "conditional_statements": true,
                    "looping": true,
                    "patterns": true,
                    "number_operations": true,
                    "number_problems": true,
                    "arrays": true,
                    "strings": true,
                    "functions_pointers": true,
                    "structures": true
                }
            },
            "assessments": {
                "enabled": false,
                "modules": {
                    "phase_1": false,
                    "phase_2": false,
                    "phase_3": false,
                    "final": false
                }
            },
            "company_specific": {
                "enabled": false,
                "modules": {
                    "accenture": false,
                    "cts": false,
                    "capgemini": false,
                    "infosys": false,
                    "tcs": false,
                    "wipro": false,
                    "zoho": false
                }
            },
            "special_tracks": {
                "enabled": false,
                "modules": {
                    "real_time_problems": false
                }
            },
            "dsa": {
                "enabled": false,
                "modules": {}
            },
            "advanced_topics": {
                "enabled": false,
                "modules": {}
            },
            "projects": {
                "enabled": false,
                "modules": {}
            },
            "interview_prep": {
                "enabled": false,
                "modules": {}
            }
        }
    },
    {
        "user_info": {
            "email": "tbarathkumar37@gmail.com",
            "year": "2K24",
            "department": "BCOM_CA"
        },
        "access_permissions": {
            "fundamentals": {
                "enabled": true,
                "modules": {
                    "basic_io": true,
                    "conditional_statements": true,
                    "looping": true,
                    "patterns": true,
                    "number_operations": true,
                    "number_problems": true,
                    "arrays": true,
                    "strings": true,
                    "functions_pointers": true,
                    "structures": true
                }
            },
            "assessments": {
                "enabled": false,
                "modules": {
                    "phase_1": false,
                    "phase_2": false,
                    "phase_3": false,
                    "final": false
                }
            },
            "company_specific": {
                "enabled": false,
                "modules": {
                    "accenture": false,
                    "cts": false,
                    "capgemini": false,
                    "infosys": false,
                    "tcs": false,
                    "wipro": false,
                    "zoho": false
                }
            },
            "special_tracks": {
                "enabled": false,
                "modules": {
                    "real_time_problems": false
                }
            },
            "dsa": {
                "enabled": false,
                "modules": {}
            },
            "advanced_topics": {
                "enabled": false,
                "modules": {}
            },
            "projects": {
                "enabled": false,
                "modules": {}
            },
            "interview_prep": {
                "enabled": false,
                "modules": {}
            }
        }
    },
    {
        "user_info": {
            "email": "dheerkadharshini23@gmail.com",
            "year": "2K24",
            "department": "BCOM_CA"
        },
        "access_permissions": {
            "fundamentals": {
                "enabled": true,
                "modules": {
                    "basic_io": true,
                    "conditional_statements": true,
                    "looping": true,
                    "patterns": true,
                    "number_operations": true,
                    "number_problems": true,
                    "arrays": true,
                    "strings": true,
                    "functions_pointers": true,
                    "structures": true
                }
            },
            "assessments": {
                "enabled": false,
                "modules": {
                    "phase_1": false,
                    "phase_2": false,
                    "phase_3": false,
                    "final": false
                }
            },
            "company_specific": {
                "enabled": false,
                "modules": {
                    "accenture": false,
                    "cts": false,
                    "capgemini": false,
                    "infosys": false,
                    "tcs": false,
                    "wipro": false,
                    "zoho": false
                }
            },
            "special_tracks": {
                "enabled": false,
                "modules": {
                    "real_time_problems": false
                }
            },
            "dsa": {
                "enabled": false,
                "modules": {}
            },
            "advanced_topics": {
                "enabled": false,
                "modules": {}
            },
            "projects": {
                "enabled": false,
                "modules": {}
            },
            "interview_prep": {
                "enabled": false,
                "modules": {}
            }
        }
    },
    {
        "user_info": {
            "email": "Kavivignesh1996@gmail.com",
            "year": "2K24",
            "department": "BSC_CS"
        },
        "access_permissions": {
            "fundamentals": {
                "enabled": true,
                "modules": {
                    "basic_io": true,
                    "conditional_statements": true,
                    "looping": true,
                    "patterns": true,
                    "number_operations": true,
                    "number_problems": true,
                    "arrays": true,
                    "strings": true,
                    "functions_pointers": true,
                    "structures": true
                }
            },
            "assessments": {
                "enabled": false,
                "modules": {
                    "phase_1": false,
                    "phase_2": false,
                    "phase_3": false,
                    "final": false
                }
            },
            "company_specific": {
                "enabled": false,
                "modules": {
                    "accenture": false,
                    "cts": false,
                    "capgemini": false,
                    "infosys": false,
                    "tcs": false,
                    "wipro": false,
                    "zoho": false
                }
            },
            "special_tracks": {
                "enabled": false,
                "modules": {
                    "real_time_problems": false
                }
            },
            "dsa": {
                "enabled": false,
                "modules": {}
            },
            "advanced_topics": {
                "enabled": false,
                "modules": {}
            },
            "projects": {
                "enabled": false,
                "modules": {}
            },
            "interview_prep": {
                "enabled": false,
                "modules": {}
            }
        }
    },
    {
        "user_info": {
            "email": "selvabharath2211@gmail.com",
            "year": "2K24",
            "department": "BSC_CS"
        },
        "access_permissions": {
            "fundamentals": {
                "enabled": true,
                "modules": {
                    "basic_io": true,
                    "conditional_statements": true,
                    "looping": true,
                    "patterns": true,
                    "number_operations": true,
                    "number_problems": true,
                    "arrays": true,
                    "strings": true,
                    "functions_pointers": true,
                    "structures": true
                }
            },
            "assessments": {
                "enabled": false,
                "modules": {
                    "phase_1": false,
                    "phase_2": false,
                    "phase_3": false,
                    "final": false
                }
            },
            "company_specific": {
                "enabled": false,
                "modules": {
                    "accenture": false,
                    "cts": false,
                    "capgemini": false,
                    "infosys": false,
                    "tcs": false,
                    "wipro": false,
                    "zoho": false
                }
            },
            "special_tracks": {
                "enabled": false,
                "modules": {
                    "real_time_problems": false
                }
            },
            "dsa": {
                "enabled": false,
                "modules": {}
            },
            "advanced_topics": {
                "enabled": false,
                "modules": {}
            },
            "projects": {
                "enabled": false,
                "modules": {}
            },
            "interview_prep": {
                "enabled": false,
                "modules": {}
            }
        }
    },
    {
        "user_info": {
            "email": "prasantharun145@gmail.com",
            "year": "2K23",
            "department": "BCA"
        },
        "access_permissions": {
            "fundamentals": {
                "enabled": true,
                "modules": {
                    "basic_io": true,
                    "conditional_statements": true,
                    "looping": true,
                    "patterns": true,
                    "number_operations": true,
                    "number_problems": true,
                    "arrays": true,
                    "strings": true,
                    "functions_pointers": true,
                    "structures": true
                }
            },
            "assessments": {
                "enabled": false,
                "modules": {
                    "phase_1": false,
                    "phase_2": false,
                    "phase_3": false,
                    "final": false
                }
            },
            "company_specific": {
                "enabled": false,
                "modules": {
                    "accenture": false,
                    "cts": false,
                    "capgemini": false,
                    "infosys": false,
                    "tcs": false,
                    "wipro": false,
                    "zoho": false
                }
            },
            "special_tracks": {
                "enabled": false,
                "modules": {
                    "real_time_problems": false
                }
            },
            "dsa": {
                "enabled": false,
                "modules": {}
            },
            "advanced_topics": {
                "enabled": false,
                "modules": {}
            },
            "projects": {
                "enabled": false,
                "modules": {}
            },
            "interview_prep": {
                "enabled": false,
                "modules": {}
            }
        }
    },
    {
        "user_info": {
            "email": "ilaki6569@gmail.com",
            "year": "2K23",
            "department": "BCA"
        },
        "access_permissions": {
            "fundamentals": {
                "enabled": true,
                "modules": {
                    "basic_io": true,
                    "conditional_statements": true,
                    "looping": true,
                    "patterns": true,
                    "number_operations": true,
                    "number_problems": true,
                    "arrays": true,
                    "strings": true,
                    "functions_pointers": true,
                    "structures": true
                }
            },
            "assessments": {
                "enabled": false,
                "modules": {
                    "phase_1": false,
                    "phase_2": false,
                    "phase_3": false,
                    "final": false
                }
            },
            "company_specific": {
                "enabled": false,
                "modules": {
                    "accenture": false,
                    "cts": false,
                    "capgemini": false,
                    "infosys": false,
                    "tcs": false,
                    "wipro": false,
                    "zoho": false
                }
            },
            "special_tracks": {
                "enabled": false,
                "modules": {
                    "real_time_problems": false
                }
            },
            "dsa": {
                "enabled": false,
                "modules": {}
            },
            "advanced_topics": {
                "enabled": false,
                "modules": {}
            },
            "projects": {
                "enabled": false,
                "modules": {}
            },
            "interview_prep": {
                "enabled": false,
                "modules": {}
            }
        }
    },
    {
        "user_info": {
            "email": "sivakishor0803@gmail.com",
            "year": "2K23",
            "department": "BCA"
        },
        "access_permissions": {
            "fundamentals": {
                "enabled": true,
                "modules": {
                    "basic_io": true,
                    "conditional_statements": true,
                    "looping": true,
                    "patterns": true,
                    "number_operations": true,
                    "number_problems": true,
                    "arrays": true,
                    "strings": true,
                    "functions_pointers": true,
                    "structures": true
                }
            },
            "assessments": {
                "enabled": false,
                "modules": {
                    "phase_1": false,
                    "phase_2": false,
                    "phase_3": false,
                    "final": false
                }
            },
            "company_specific": {
                "enabled": false,
                "modules": {
                    "accenture": false,
                    "cts": false,
                    "capgemini": false,
                    "infosys": false,
                    "tcs": false,
                    "wipro": false,
                    "zoho": false
                }
            },
            "special_tracks": {
                "enabled": false,
                "modules": {
                    "real_time_problems": false
                }
            },
            "dsa": {
                "enabled": false,
                "modules": {}
            },
            "advanced_topics": {
                "enabled": false,
                "modules": {}
            },
            "projects": {
                "enabled": false,
                "modules": {}
            },
            "interview_prep": {
                "enabled": false,
                "modules": {}
            }
        }
    },
    {
        "user_info": {
            "email": "kavipriyam305@gmail.com",
            "year": "2K23",
            "department": "BCA"
        },
        "access_permissions": {
            "fundamentals": {
                "enabled": true,
                "modules": {
                    "basic_io": true,
                    "conditional_statements": true,
                    "looping": true,
                    "patterns": true,
                    "number_operations": true,
                    "number_problems": true,
                    "arrays": true,
                    "strings": true,
                    "functions_pointers": true,
                    "structures": true
                }
            },
            "assessments": {
                "enabled": false,
                "modules": {
                    "phase_1": false,
                    "phase_2": false,
                    "phase_3": false,
                    "final": false
                }
            },
            "company_specific": {
                "enabled": false,
                "modules": {
                    "accenture": false,
                    "cts": false,
                    "capgemini": false,
                    "infosys": false,
                    "tcs": false,
                    "wipro": false,
                    "zoho": false
                }
            },
            "special_tracks": {
                "enabled": false,
                "modules": {
                    "real_time_problems": false
                }
            },
            "dsa": {
                "enabled": false,
                "modules": {}
            },
            "advanced_topics": {
                "enabled": false,
                "modules": {}
            },
            "projects": {
                "enabled": false,
                "modules": {}
            },
            "interview_prep": {
                "enabled": false,
                "modules": {}
            }
        }
    },
    {
        "user_info": {
            "email": "ragupathiperumal96@gmail.com",
            "year": "2K23",
            "department": "BCA"
        },
        "access_permissions": {
            "fundamentals": {
                "enabled": true,
                "modules": {
                    "basic_io": true,
                    "conditional_statements": true,
                    "looping": true,
                    "patterns": true,
                    "number_operations": true,
                    "number_problems": true,
                    "arrays": true,
                    "strings": true,
                    "functions_pointers": true,
                    "structures": true
                }
            },
            "assessments": {
                "enabled": false,
                "modules": {
                    "phase_1": false,
                    "phase_2": false,
                    "phase_3": false,
                    "final": false
                }
            },
            "company_specific": {
                "enabled": false,
                "modules": {
                    "accenture": false,
                    "cts": false,
                    "capgemini": false,
                    "infosys": false,
                    "tcs": false,
                    "wipro": false,
                    "zoho": false
                }
            },
            "special_tracks": {
                "enabled": false,
                "modules": {
                    "real_time_problems": false
                }
            },
            "dsa": {
                "enabled": false,
                "modules": {}
            },
            "advanced_topics": {
                "enabled": false,
                "modules": {}
            },
            "projects": {
                "enabled": false,
                "modules": {}
            },
            "interview_prep": {
                "enabled": false,
                "modules": {}
            }
        }
    },
    {
        "user_info": {
            "email": "sivajeeva6369403@gmail.com",
            "year": "2K23",
            "department": "BCA"
        },
        "access_permissions": {
            "fundamentals": {
                "enabled": true,
                "modules": {
                    "basic_io": true,
                    "conditional_statements": true,
                    "looping": true,
                    "patterns": true,
                    "number_operations": true,
                    "number_problems": true,
                    "arrays": true,
                    "strings": true,
                    "functions_pointers": true,
                    "structures": true
                }
            },
            "assessments": {
                "enabled": false,
                "modules": {
                    "phase_1": false,
                    "phase_2": false,
                    "phase_3": false,
                    "final": false
                }
            },
            "company_specific": {
                "enabled": false,
                "modules": {
                    "accenture": false,
                    "cts": false,
                    "capgemini": false,
                    "infosys": false,
                    "tcs": false,
                    "wipro": false,
                    "zoho": false
                }
            },
            "special_tracks": {
                "enabled": false,
                "modules": {
                    "real_time_problems": false
                }
            },
            "dsa": {
                "enabled": false,
                "modules": {}
            },
            "advanced_topics": {
                "enabled": false,
                "modules": {}
            },
            "projects": {
                "enabled": false,
                "modules": {}
            },
            "interview_prep": {
                "enabled": false,
                "modules": {}
            }
        }
    },
    {
        "user_info": {
            "email": "bk4362804@gmail.com",
            "year": "2K23",
            "department": "BCOM_CA"
        },
        "access_permissions": {
            "fundamentals": {
                "enabled": true,
                "modules": {
                    "basic_io": true,
                    "conditional_statements": true,
                    "looping": true,
                    "patterns": true,
                    "number_operations": true,
                    "number_problems": true,
                    "arrays": true,
                    "strings": true,
                    "functions_pointers": true,
                    "structures": true
                }
            },
            "assessments": {
                "enabled": false,
                "modules": {
                    "phase_1": false,
                    "phase_2": false,
                    "phase_3": false,
                    "final": false
                }
            },
            "company_specific": {
                "enabled": false,
                "modules": {
                    "accenture": false,
                    "cts": false,
                    "capgemini": false,
                    "infosys": false,
                    "tcs": false,
                    "wipro": false,
                    "zoho": false
                }
            },
            "special_tracks": {
                "enabled": false,
                "modules": {
                    "real_time_problems": false
                }
            },
            "dsa": {
                "enabled": false,
                "modules": {}
            },
            "advanced_topics": {
                "enabled": false,
                "modules": {}
            },
            "projects": {
                "enabled": false,
                "modules": {}
            },
            "interview_prep": {
                "enabled": false,
                "modules": {}
            }
        }
    },
    {
        "user_info": {
            "email": "mohangopi1824@gmail.com",
            "year": "2K23",
            "department": "BCOM_CA"
        },
        "access_permissions": {
            "fundamentals": {
                "enabled": true,
                "modules": {
                    "basic_io": true,
                    "conditional_statements": true,
                    "looping": true,
                    "patterns": true,
                    "number_operations": true,
                    "number_problems": true,
                    "arrays": true,
                    "strings": true,
                    "functions_pointers": true,
                    "structures": true
                }
            },
            "assessments": {
                "enabled": false,
                "modules": {
                    "phase_1": false,
                    "phase_2": false,
                    "phase_3": false,
                    "final": false
                }
            },
            "company_specific": {
                "enabled": false,
                "modules": {
                    "accenture": false,
                    "cts": false,
                    "capgemini": false,
                    "infosys": false,
                    "tcs": false,
                    "wipro": false,
                    "zoho": false
                }
            },
            "special_tracks": {
                "enabled": false,
                "modules": {
                    "real_time_problems": false
                }
            },
            "dsa": {
                "enabled": false,
                "modules": {}
            },
            "advanced_topics": {
                "enabled": false,
                "modules": {}
            },
            "projects": {
                "enabled": false,
                "modules": {}
            },
            "interview_prep": {
                "enabled": false,
                "modules": {}
            }
        }
    },
    {
        "user_info": {
            "email": "naveenkumarravi2005@gmail.com",
            "year": "2K23",
            "department": "BCOM_CA"
        },
        "access_permissions": {
            "fundamentals": {
                "enabled": true,
                "modules": {
                    "basic_io": true,
                    "conditional_statements": true,
                    "looping": true,
                    "patterns": true,
                    "number_operations": true,
                    "number_problems": true,
                    "arrays": true,
                    "strings": true,
                    "functions_pointers": true,
                    "structures": true
                }
            },
            "assessments": {
                "enabled": false,
                "modules": {
                    "phase_1": false,
                    "phase_2": false,
                    "phase_3": false,
                    "final": false
                }
            },
            "company_specific": {
                "enabled": false,
                "modules": {
                    "accenture": false,
                    "cts": false,
                    "capgemini": false,
                    "infosys": false,
                    "tcs": false,
                    "wipro": false,
                    "zoho": false
                }
            },
            "special_tracks": {
                "enabled": false,
                "modules": {
                    "real_time_problems": false
                }
            },
            "dsa": {
                "enabled": false,
                "modules": {}
            },
            "advanced_topics": {
                "enabled": false,
                "modules": {}
            },
            "projects": {
                "enabled": false,
                "modules": {}
            },
            "interview_prep": {
                "enabled": false,
                "modules": {}
            }
        }
    },
    {
        "user_info": {
            "email": "gtgowtham179@gmail.com",
            "year": "2K23",
            "department": "BCOM_CA"
        },
        "access_permissions": {
            "fundamentals": {
                "enabled": true,
                "modules": {
                    "basic_io": true,
                    "conditional_statements": true,
                    "looping": true,
                    "patterns": true,
                    "number_operations": true,
                    "number_problems": true,
                    "arrays": true,
                    "strings": true,
                    "functions_pointers": true,
                    "structures": true
                }
            },
            "assessments": {
                "enabled": false,
                "modules": {
                    "phase_1": false,
                    "phase_2": false,
                    "phase_3": false,
                    "final": false
                }
            },
            "company_specific": {
                "enabled": false,
                "modules": {
                    "accenture": false,
                    "cts": false,
                    "capgemini": false,
                    "infosys": false,
                    "tcs": false,
                    "wipro": false,
                    "zoho": false
                }
            },
            "special_tracks": {
                "enabled": false,
                "modules": {
                    "real_time_problems": false
                }
            },
            "dsa": {
                "enabled": false,
                "modules": {}
            },
            "advanced_topics": {
                "enabled": false,
                "modules": {}
            },
            "projects": {
                "enabled": false,
                "modules": {}
            },
            "interview_prep": {
                "enabled": false,
                "modules": {}
            }
        }
    },
    {
        "user_info": {
            "email": "ramyaselvaraj1975@gmail.com",
            "year": "2K23",
            "department": "BSC_CS"
        },
        "access_permissions": {
            "fundamentals": {
                "enabled": true,
                "modules": {
                    "basic_io": true,
                    "conditional_statements": true,
                    "looping": true,
                    "patterns": true,
                    "number_operations": true,
                    "number_problems": true,
                    "arrays": true,
                    "strings": true,
                    "functions_pointers": true,
                    "structures": true
                }
            },
            "assessments": {
                "enabled": false,
                "modules": {
                    "phase_1": false,
                    "phase_2": false,
                    "phase_3": false,
                    "final": false
                }
            },
            "company_specific": {
                "enabled": false,
                "modules": {
                    "accenture": false,
                    "cts": false,
                    "capgemini": false,
                    "infosys": false,
                    "tcs": false,
                    "wipro": false,
                    "zoho": false
                }
            },
            "special_tracks": {
                "enabled": false,
                "modules": {
                    "real_time_problems": false
                }
            },
            "dsa": {
                "enabled": false,
                "modules": {}
            },
            "advanced_topics": {
                "enabled": false,
                "modules": {}
            },
            "projects": {
                "enabled": false,
                "modules": {}
            },
            "interview_prep": {
                "enabled": false,
                "modules": {}
            }
        }
    }
]